README.md
setup.py
asm_6502/__init__.py
asm_6502/assemble.py
asm_6502/grammar.py
asm_6502/parsetab.py
mos_6502_restricted_assembler.egg-info/PKG-INFO
mos_6502_restricted_assembler.egg-info/SOURCES.txt
mos_6502_restricted_assembler.egg-info/dependency_links.txt
mos_6502_restricted_assembler.egg-info/requires.txt
mos_6502_restricted_assembler.egg-info/top_level.txt
tests/__init__.py
tests/asm_arithmetic/__init__.py
tests/asm_arithmetic/test_asm_adc.py
tests/asm_arithmetic/test_asm_anc.py
tests/asm_arithmetic/test_asm_arr.py
tests/asm_arithmetic/test_asm_asr.py
tests/asm_arithmetic/test_asm_cmp.py
tests/asm_arithmetic/test_asm_cpx.py
tests/asm_arithmetic/test_asm_cpy.py
tests/asm_arithmetic/test_asm_dcp.py
tests/asm_arithmetic/test_asm_isc.py
tests/asm_arithmetic/test_asm_rla.py
tests/asm_arithmetic/test_asm_rra.py
tests/asm_arithmetic/test_asm_sbc.py
tests/asm_arithmetic/test_asm_sbx.py
tests/asm_arithmetic/test_asm_slo.py
tests/asm_arithmetic/test_asm_sre.py
tests/asm_arithmetic/test_asm_xaa.py
tests/asm_branch/__init__.py
tests/asm_branch/test_asm_bcc.py
tests/asm_branch/test_asm_bcs.py
tests/asm_branch/test_asm_beq.py
tests/asm_branch/test_asm_bmi.py
tests/asm_branch/test_asm_bne.py
tests/asm_branch/test_asm_bpl.py
tests/asm_branch/test_asm_bvc.py
tests/asm_branch/test_asm_bvs.py
tests/asm_increment/__init__.py
tests/asm_increment/test_asm_dec.py
tests/asm_increment/test_asm_dex.py
tests/asm_increment/test_asm_dey.py
tests/asm_increment/test_asm_inc.py
tests/asm_increment/test_asm_inx.py
tests/asm_increment/test_asm_iny.py
tests/asm_jump/__init__.py
tests/asm_jump/test_asm_jmp.py
tests/asm_jump/test_asm_jsr.py
tests/asm_jump/test_asm_rts.py
tests/asm_load/__init__.py
tests/asm_load/test_asm_las.py
tests/asm_load/test_asm_lax.py
tests/asm_load/test_asm_lda.py
tests/asm_load/test_asm_ldx.py
tests/asm_load/test_asm_ldy.py
tests/asm_logical/__init__.py
tests/asm_logical/test_asm_and.py
tests/asm_logical/test_asm_bit.py
tests/asm_logical/test_asm_eor.py
tests/asm_logical/test_asm_ora.py
tests/asm_pseudo/__init__.py
tests/asm_pseudo/test_asm_byte.py
tests/asm_pseudo/test_asm_end.py
tests/asm_pseudo/test_asm_word.py
tests/asm_shift/__init__.py
tests/asm_shift/test_asm_asl.py
tests/asm_shift/test_asm_lsr.py
