Metadata-Version: 2.1
Name: mos-6502-restricted-assembler
Version: 0.1.1
Summary: A 6502 assembler with restricted functions
Home-page: https://github.com/CyberZHG/mos-6502-restricted-assembler
Author: CyberZHG
Author-email: CyberZHG@users.noreply.github.com
License: MIT
Platform: UNKNOWN
Classifier: Programming Language :: Python :: 3
Classifier: License :: OSI Approved :: MIT License
Classifier: Operating System :: OS Independent
